neco/__init__.py
neco/cli/__init__.py
neco/cli/agent_cli.py
neco/cli/tools_cli.py
neco/core/__init__.py
neco/core/utils/crypto.py
neco/core/utils/template_loader.py
neco/core/utils/timing_decorator.py
neco/llm/__init__.py
neco/llm/agent/__init__.py
neco/llm/agent/chatbot_workflow.py
neco/llm/agent/deep_agent.py
neco/llm/agent/lats_agent.py
neco/llm/agent/plan_and_execute_agent.py
neco/llm/agent/react_agent.py
neco/llm/agent/supervisor_multi_agent.py
neco/llm/chain/entity.py
neco/llm/chain/graph.py
neco/llm/chain/node.py
neco/llm/chain/state.py
neco/llm/chunk/__init__.py
neco/llm/chunk/base_chunk.py
neco/llm/chunk/fixed_size_chunk.py
neco/llm/chunk/full_chunk.py
neco/llm/chunk/recursive_chunk.py
neco/llm/chunk/semantic_chunk.py
neco/llm/common/__init__.py
neco/llm/common/structured_output_parser.py
neco/llm/common/tracing.py
neco/llm/embed/embed_manager.py
neco/llm/loader/__init__.py
neco/llm/loader/doc_loader.py
neco/llm/loader/excel_loader.py
neco/llm/loader/image_loader.py
neco/llm/loader/markdown_loader.py
neco/llm/loader/pdf_loader.py
neco/llm/loader/ppt_loader.py
neco/llm/loader/raw_loader.py
neco/llm/loader/text_loader.py
neco/llm/loader/website_loader.py
neco/llm/rag/__init__.py
neco/llm/rag/graph_rag_entity.py
neco/llm/rag/naive_rag_entity.py
neco/llm/rag/rag_enhance_entity.py
neco/llm/rag/enhance/__init__.py
neco/llm/rag/enhance/qa_generation.py
neco/llm/rag/graph_rag/__init__.py
neco/llm/rag/graph_rag/graphiti/__init__.py
neco/llm/rag/graph_rag/graphiti/graphiti_rag.py
neco/llm/rag/graph_rag/graphiti/metis_embedder.py
neco/llm/rag/graph_rag/graphiti/metis_embedder_config.py
neco/llm/rag/graph_rag/graphiti/metis_reranker_client.py
neco/llm/rag/graph_rag/graphiti/metis_reranker_config.py
neco/llm/rag/graph_rag/graphiti/openai_client_patch.py
neco/llm/rag/naive_rag/__init__.py
neco/llm/rag/naive_rag/pgvector/__init__.py
neco/llm/rag/naive_rag/pgvector/database_connection_pool.py
neco/llm/rag/naive_rag/pgvector/database_manager.py
neco-1.0.14.dist-info/licenses/LICENSE
neco-1.0.14.dist-info/METADATA
neco-1.0.14.dist-info/WHEEL
neco-1.0.14.dist-info/entry_points.txt
neco-1.0.14.dist-info/top_level.txt
neco-1.0.14.dist-info/RECORD
