Metadata-Version: 2.4
Name: neco
Version: 1.0.14
Summary: Add your description here
Requires-Python: >=3.12
License-File: LICENSE
Provides-Extra: core
Requires-Dist: networkx==3.5; extra == "core"
Requires-Dist: pycryptodome==3.23.0; extra == "core"
Requires-Dist: fire>=0.7.1; extra == "core"
Requires-Dist: loguru==0.7.3; extra == "core"
Requires-Dist: psycopg2-binary==2.9.9; extra == "core"
Requires-Dist: setuptools>=68; extra == "core"
Requires-Dist: python-dotenv==1.1.0; extra == "core"
Requires-Dist: tqdm==4.66.4; extra == "core"
Requires-Dist: singleton-decorator==1.0.0; extra == "core"
Requires-Dist: falkordb==1.2.0; extra == "core"
Requires-Dist: pyarmor==9.1.5; extra == "core"
Requires-Dist: pandas==2.2.2; extra == "core"
Requires-Dist: pillow==10.3.0; extra == "core"
Requires-Dist: redis==5.0.1; extra == "core"
Requires-Dist: jinja2==3.1.4; extra == "core"
Requires-Dist: nanoid==2.0.0; extra == "core"
Requires-Dist: diskcache==5.6.3; extra == "core"
Requires-Dist: jieba==0.42.1; extra == "core"
Provides-Extra: sanic
Requires-Dist: sanic==25.3.0; extra == "sanic"
Requires-Dist: sanic-ext==23.12.0; extra == "sanic"
Requires-Dist: Sanic-HTTPAuth==0.2.0; extra == "sanic"
Provides-Extra: mlflow
Requires-Dist: mlflow==3.3.2; extra == "mlflow"
Requires-Dist: boto3==1.38.41; extra == "mlflow"
Provides-Extra: doc-parser
Requires-Dist: python-pptx==0.6.23; extra == "doc-parser"
Requires-Dist: python-docx==1.1.2; extra == "doc-parser"
Requires-Dist: openpyxl==3.1.5; extra == "doc-parser"
Requires-Dist: tabulate==0.9.0; extra == "doc-parser"
Requires-Dist: jpype1==1.5.2; extra == "doc-parser"
Requires-Dist: pymupdf==1.24.5; extra == "doc-parser"
Requires-Dist: markdownify==0.12.1; extra == "doc-parser"
Requires-Dist: tabula-py==2.10.0; extra == "doc-parser"
Provides-Extra: mlops
Requires-Dist: scikit-learn==1.6.1; extra == "mlops"
Requires-Dist: tsfresh==0.21.1; extra == "mlops"
Requires-Dist: hyperopt==0.2.7; extra == "mlops"
Provides-Extra: llm
Requires-Dist: ag-ui-protocol==0.1.10; extra == "llm"
Requires-Dist: langchain==1.0.5; extra == "llm"
Requires-Dist: langgraph==1.0.3; extra == "llm"
Requires-Dist: langchain-openai==1.0.2; extra == "llm"
Requires-Dist: graphiti-core==0.23.1; extra == "llm"
Requires-Dist: json-repair==0.53.0; extra == "llm"
Requires-Dist: duckduckgo-search==8.1.1; extra == "llm"
Requires-Dist: langchain-postgres==0.0.16; extra == "llm"
Requires-Dist: langgraph-checkpoint-postgres==3.0.1; extra == "llm"
Requires-Dist: langchain-mcp-adapters==0.1.12; extra == "llm"
Requires-Dist: langchain-community==0.4.1; extra == "llm"
Requires-Dist: langgraph-supervisor>=0.0.30; extra == "llm"
Requires-Dist: langchain-experimental==0.4.0; extra == "llm"
Requires-Dist: deepagents==0.2.5; extra == "llm"
Provides-Extra: devops
Requires-Dist: python-jenkins==1.8.2; extra == "devops"
Requires-Dist: kubernetes==32.0.1; extra == "devops"
Provides-Extra: ocr
Requires-Dist: azure-cognitiveservices-vision-computervision==0.9.0; extra == "ocr"
Provides-Extra: all
Requires-Dist: neco[mlops]; extra == "all"
Requires-Dist: neco[llm]; extra == "all"
Requires-Dist: neco[devops]; extra == "all"
Requires-Dist: neco[doc_parser]; extra == "all"
Requires-Dist: neco[sanic]; extra == "all"
Requires-Dist: neco[ocr]; extra == "all"
Requires-Dist: neco[core]; extra == "all"
Dynamic: license-file
